CHANGES.md
LICENSE
MANIFEST.in
README.md
setup.py
django_exportdata.egg-info/PKG-INFO
django_exportdata.egg-info/SOURCES.txt
django_exportdata.egg-info/dependency_links.txt
django_exportdata.egg-info/requires.txt
django_exportdata.egg-info/top_level.txt
exportdata/__init__.py
exportdata/models.py
exportdata/management/__init__.py
exportdata/management/commands/__init__.py
exportdata/management/commands/exportdata.py